greptimedb_sqlalchemy/__init__.py
greptimedb_sqlalchemy/dbapi.py
greptimedb_sqlalchemy/superset.py
greptimedb_sqlalchemy/types.py
greptimedb_sqlalchemy-0.1.7.dist-info/METADATA
greptimedb_sqlalchemy-0.1.7.dist-info/WHEEL
greptimedb_sqlalchemy-0.1.7.dist-info/entry_points.txt
greptimedb_sqlalchemy-0.1.7.dist-info/RECORD
