Metadata-Version: 2.3
Name: greptimedb-sqlalchemy
Version: 0.1.7
Summary: SQLAlchemy support for GreptimeDB
Author-email: Ning Sun <sunning@greptime.com>
Classifier: Intended Audience :: Developers
Classifier: License :: OSI Approved :: Apache Software License
Classifier: Programming Language :: Python :: 3.9
Classifier: Programming Language :: Python :: 3.10
Classifier: Programming Language :: Python :: 3.11
Classifier: Topic :: Database
Requires-Python: >=3.9
Requires-Dist: psycopg2-binary>=2.9.9
Requires-Dist: sqlalchemy<2,>=1.4
